{
  "id": "god-of-ruin",
  "title": "God of Ruin",
  "author": "Rina Kent",
  "description": "I’m out for revenge. After careful planning, I gave the man who messed with my family a taste of his own medicine. I thought it’d end there. It didn’t. Landon King is a genius artist, a posh rich boy, and my worst nightmare. He’s decided that I’m the new addition to his chess game. Too bad for him, I’m no pawn. If he hits, I hit back, twice as hard and with the same hostility. He says he’ll ruin me. Little does he know that ruination goes both ways. This book is a dark unconventional romance and",
  "filename": "God of Ruin - Rina Kent - Legacy of Gods #4.epub",
  "totalWords": 123593,
  "totalPages": 124,
  "totalChapters": 50,
  "series": "Legacy of Gods",
  "bookNumber": 4,
  "totalBooksInSeries": 6,
  "seriesStatus": "complete",
  "allBooksInSeries": [
    {
      "number": 1,
      "title": "God of Malice"
    },
    {
      "number": 2,
      "title": "God of Pain"
    },
    {
      "number": 3,
      "title": "God of Wrath"
    },
    {
      "number": 4,
      "title": "God of Ruin"
    },
    {
      "number": 5,
      "title": "God of Fury"
    },
    {
      "number": 6,
      "title": "God of War"
    }
  ],
  "chapters": [
    {
      "index": 1,
      "title": "Chapter 1",
      "wordCount": 138,
      "pageCount": 1,
      "startPage": 1
    },
    {
      "index": 2,
      "title": "Chapter 2",
      "wordCount": 112,
      "pageCount": 1,
      "startPage": 2
    },
    {
      "index": 3,
      "title": "Chapter 3",
      "wordCount": 73,
      "pageCount": 1,
      "startPage": 3
    },
    {
      "index": 4,
      "title": "Chapter 4",
      "wordCount": 90,
      "pageCount": 1,
      "startPage": 4
    },
    {
      "index": 5,
      "title": "Chapter 5",
      "wordCount": 96,
      "pageCount": 1,
      "startPage": 5
    },
    {
      "index": 6,
      "title": "Chapter 6",
      "wordCount": 2813,
      "pageCount": 3,
      "startPage": 6
    },
    {
      "index": 7,
      "title": "Chapter 7",
      "wordCount": 2231,
      "pageCount": 3,
      "startPage": 9
    },
    {
      "index": 8,
      "title": "Chapter 8",
      "wordCount": 2132,
      "pageCount": 3,
      "startPage": 12
    },
    {
      "index": 9,
      "title": "Chapter 9",
      "wordCount": 2293,
      "pageCount": 3,
      "startPage": 15
    },
    {
      "index": 10,
      "title": "Chapter 10",
      "wordCount": 2268,
      "pageCount": 3,
      "startPage": 18
    },
    {
      "index": 11,
      "title": "Chapter 11",
      "wordCount": 2645,
      "pageCount": 3,
      "startPage": 21
    },
    {
      "index": 12,
      "title": "Chapter 12",
      "wordCount": 3263,
      "pageCount": 4,
      "startPage": 24
    },
    {
      "index": 13,
      "title": "Chapter 13",
      "wordCount": 3774,
      "pageCount": 4,
      "startPage": 28
    },
    {
      "index": 14,
      "title": "Chapter 14",
      "wordCount": 2667,
      "pageCount": 3,
      "startPage": 32
    },
    {
      "index": 15,
      "title": "Chapter 15",
      "wordCount": 4626,
      "pageCount": 5,
      "startPage": 35
    },
    {
      "index": 16,
      "title": "Chapter 16",
      "wordCount": 2800,
      "pageCount": 3,
      "startPage": 40
    },
    {
      "index": 17,
      "title": "Chapter 17",
      "wordCount": 3557,
      "pageCount": 4,
      "startPage": 43
    },
    {
      "index": 18,
      "title": "Chapter 18",
      "wordCount": 3113,
      "pageCount": 4,
      "startPage": 47
    },
    {
      "index": 19,
      "title": "Chapter 19",
      "wordCount": 2627,
      "pageCount": 3,
      "startPage": 51
    },
    {
      "index": 20,
      "title": "Chapter 20",
      "wordCount": 3076,
      "pageCount": 4,
      "startPage": 54
    },
    {
      "index": 21,
      "title": "Chapter 21",
      "wordCount": 2789,
      "pageCount": 3,
      "startPage": 58
    },
    {
      "index": 22,
      "title": "Chapter 22",
      "wordCount": 3858,
      "pageCount": 4,
      "startPage": 61
    },
    {
      "index": 23,
      "title": "Chapter 23",
      "wordCount": 3554,
      "pageCount": 4,
      "startPage": 65
    },
    {
      "index": 24,
      "title": "Chapter 24",
      "wordCount": 3516,
      "pageCount": 4,
      "startPage": 69
    },
    {
      "index": 25,
      "title": "Chapter 25",
      "wordCount": 2894,
      "pageCount": 3,
      "startPage": 73
    },
    {
      "index": 26,
      "title": "Chapter 26",
      "wordCount": 3298,
      "pageCount": 4,
      "startPage": 76
    },
    {
      "index": 27,
      "title": "Chapter 27",
      "wordCount": 3682,
      "pageCount": 4,
      "startPage": 80
    },
    {
      "index": 28,
      "title": "Chapter 28",
      "wordCount": 2979,
      "pageCount": 3,
      "startPage": 84
    },
    {
      "index": 29,
      "title": "Chapter 29",
      "wordCount": 3542,
      "pageCount": 4,
      "startPage": 87
    },
    {
      "index": 30,
      "title": "Chapter 30",
      "wordCount": 3851,
      "pageCount": 4,
      "startPage": 91
    },
    {
      "index": 31,
      "title": "Chapter 31",
      "wordCount": 3009,
      "pageCount": 4,
      "startPage": 95
    },
    {
      "index": 32,
      "title": "Chapter 32",
      "wordCount": 2934,
      "pageCount": 3,
      "startPage": 99
    },
    {
      "index": 33,
      "title": "Chapter 33",
      "wordCount": 3498,
      "pageCount": 4,
      "startPage": 102
    },
    {
      "index": 34,
      "title": "Chapter 34",
      "wordCount": 1688,
      "pageCount": 2,
      "startPage": 106
    },
    {
      "index": 35,
      "title": "Chapter 35",
      "wordCount": 1133,
      "pageCount": 2,
      "startPage": 108
    },
    {
      "index": 36,
      "title": "Chapter 36",
      "wordCount": 1404,
      "pageCount": 2,
      "startPage": 110
    },
    {
      "index": 37,
      "title": "Chapter 37",
      "wordCount": 2677,
      "pageCount": 3,
      "startPage": 112
    },
    {
      "index": 38,
      "title": "Chapter 38",
      "wordCount": 4907,
      "pageCount": 5,
      "startPage": 115
    },
    {
      "index": 39,
      "title": "Chapter 39",
      "wordCount": 2803,
      "pageCount": 3,
      "startPage": 120
    },
    {
      "index": 40,
      "title": "Chapter 40",
      "wordCount": 3220,
      "pageCount": 4,
      "startPage": 123
    },
    {
      "index": 41,
      "title": "Chapter 41",
      "wordCount": 2794,
      "pageCount": 3,
      "startPage": 127
    },
    {
      "index": 42,
      "title": "Chapter 42",
      "wordCount": 1811,
      "pageCount": 2,
      "startPage": 130
    },
    {
      "index": 43,
      "title": "Chapter 43",
      "wordCount": 3716,
      "pageCount": 4,
      "startPage": 132
    },
    {
      "index": 44,
      "title": "Chapter 44",
      "wordCount": 2463,
      "pageCount": 3,
      "startPage": 136
    },
    {
      "index": 45,
      "title": "Chapter 45",
      "wordCount": 2731,
      "pageCount": 3,
      "startPage": 139
    },
    {
      "index": 46,
      "title": "Chapter 46",
      "wordCount": 2634,
      "pageCount": 3,
      "startPage": 142
    },
    {
      "index": 47,
      "title": "Chapter 47",
      "wordCount": 1528,
      "pageCount": 2,
      "startPage": 145
    },
    {
      "index": 48,
      "title": "Chapter 48",
      "wordCount": 70,
      "pageCount": 1,
      "startPage": 147
    },
    {
      "index": 49,
      "title": "Chapter 49",
      "wordCount": 111,
      "pageCount": 1,
      "startPage": 148
    },
    {
      "index": 50,
      "title": "Chapter 50",
      "wordCount": 105,
      "pageCount": 1,
      "startPage": 149
    }
  ]
}